.gitignore
.travis.yml
NOTICE.txt
README.rst
bootstrap.py
buildout.cfg
edrnsite.funding.sublime-project
setup.cfg
setup.py
travis.cfg
docs/HISTORY.txt
docs/INSTALL.txt
docs/LICENSE.txt
edrnsite/__init__.py
edrnsite.funding.egg-info/PKG-INFO
edrnsite.funding.egg-info/SOURCES.txt
edrnsite.funding.egg-info/dependency_links.txt
edrnsite.funding.egg-info/entry_points.txt
edrnsite.funding.egg-info/namespace_packages.txt
edrnsite.funding.egg-info/not-zip-safe
edrnsite.funding.egg-info/requires.txt
edrnsite.funding.egg-info/top_level.txt
edrnsite/funding/README.rst
edrnsite/funding/__init__.py
edrnsite/funding/config.py
edrnsite/funding/configure.zcml
edrnsite/funding/interfaces.py
edrnsite/funding/testing.py
edrnsite/funding/upgrades.py
edrnsite/funding/upgrades.zcml
edrnsite/funding/browser/__init__.py
edrnsite/funding/browser/configure.zcml
edrnsite/funding/browser/views.py
edrnsite/funding/browser/images/announcement.gif
edrnsite/funding/browser/images/announcement.gif.metadata
edrnsite/funding/browser/images/funding-folder.gif
edrnsite/funding/browser/images/funding-folder.gif.metadata
edrnsite/funding/browser/images/funding-opportunity.gif
edrnsite/funding/browser/images/funding-opportunity.gif.metadata
edrnsite/funding/browser/templates/announcement.pt
edrnsite/funding/browser/templates/fundingOps.pt
edrnsite/funding/browser/templates/fundingfolder.pt
edrnsite/funding/browser/templates/fundingopportunity.pt
edrnsite/funding/content/__init__.py
edrnsite/funding/content/announcement.py
edrnsite/funding/content/configure.zcml
edrnsite/funding/content/fundingfolder.py
edrnsite/funding/content/fundingopportunity.py
edrnsite/funding/profiles/default/catalog.xml
edrnsite/funding/profiles/default/factorytool.xml
edrnsite/funding/profiles/default/metadata.xml
edrnsite/funding/profiles/default/rolemap.xml
edrnsite/funding/profiles/default/types.xml
edrnsite/funding/profiles/default/types/Announcement.xml
edrnsite/funding/profiles/default/types/Funding_Folder.xml
edrnsite/funding/profiles/default/types/Funding_Opportunity.xml
edrnsite/funding/tests/__init__.py
edrnsite/funding/tests/testDoctest.py
edrnsite/funding/tests/testSetup.py