Metadata-Version: 2.1
Name: edrnsite.funding
Version: 1.0.7
Summary: EDRN Funding Opportunities
Home-page: https://github.com/EDRN/edrnsite.funding
Author: Sean Kelly
Author-email: sean.kelly@jpl.nasa.gov
License: ALv2
Keywords: web zope plone edrn cancer biomarkers funding funds
Platform: UNKNOWN
Classifier: Development Status :: 4 - Beta
Classifier: Environment :: Web Environment
Classifier: Framework :: Plone
Classifier: Intended Audience :: Healthcare Industry
Classifier: Intended Audience :: Science/Research
Classifier: License :: OSI Approved :: Apache Software License
Classifier: Operating System :: OS Independent
Classifier: Programming Language :: Python
Classifier: Topic :: Internet :: WWW/HTTP
Classifier: Topic :: Scientific/Engineering :: Bio-Informatics
Classifier: Topic :: Software Development :: Libraries :: Python Modules
Provides-Extra: test
